docs/tarpitd.py.1.md
docs/tarpitd.py.7.md
src/tarpitd.py
src/tarpitd_import_guard.py
tarpitd-0.0.2.dist-info/METADATA
tarpitd-0.0.2.dist-info/WHEEL
tarpitd-0.0.2.dist-info/entry_points.txt
tarpitd-0.0.2.dist-info/licenses/LICENSE
tarpitd-0.0.2.dist-info/RECORD
