Metadata-Version: 2.1
Name: tarpitd
Version: 0.0.2
Summary: A daemon making a port into tarpit
Project-URL: Homepage, https://github.com/ImBearChild/tarpitd.py
Project-URL: Issues, https://github.com/ImBearChild/tarpitd.py/issues
Author-email: Nianqing Yao <imbeatchild@outlook.com>
License-File: LICENSE
Classifier: License :: OSI Approved :: Mozilla Public License 2.0 (MPL 2.0)
Classifier: Operating System :: OS Independent
Classifier: Programming Language :: Python :: 3
Classifier: Topic :: Internet
Classifier: Topic :: System :: Networking
Requires-Python: >=3.10
